setup.cfg
setup.py
pymay/__init__.py
pymay.egg-info/.DS_Store
pymay.egg-info/PKG-INFO
pymay.egg-info/SOURCES.txt
pymay.egg-info/dependency_links.txt
pymay.egg-info/not-zip-safe
pymay.egg-info/top_level.txt