Metadata-Version: 1.0
Name: pymay
Version: 1.0.0
Summary: A micro framework Google AppEngine Based
Home-page: https://github.com/jesse1983/pymay
Author: Jesse Pinheiro
Author-email: jessebpinheiro@gmail.com
License: MIT
Platform: UNKNOWN
